odoo8_addon_l10n_pe_base_vat_split-8.0.1.0.0-py2.7-nspkg.pth
odoo_addons/l10n_pe_base_vat_split/__openerp__.py
odoo_addons/l10n_pe_base_vat_split/__init__.py
odoo_addons/l10n_pe_base_vat_split/README.rst
odoo_addons/l10n_pe_base_vat_split/i18n/es.po
odoo_addons/l10n_pe_base_vat_split/model/__init__.py
odoo_addons/l10n_pe_base_vat_split/model/base_vat.py
odoo8_addon_l10n_pe_base_vat_split-8.0.1.0.0.dist-info/top_level.txt
odoo8_addon_l10n_pe_base_vat_split-8.0.1.0.0.dist-info/WHEEL
odoo8_addon_l10n_pe_base_vat_split-8.0.1.0.0.dist-info/RECORD
odoo8_addon_l10n_pe_base_vat_split-8.0.1.0.0.dist-info/metadata.json
odoo8_addon_l10n_pe_base_vat_split-8.0.1.0.0.dist-info/DESCRIPTION.rst
odoo8_addon_l10n_pe_base_vat_split-8.0.1.0.0.dist-info/METADATA
odoo8_addon_l10n_pe_base_vat_split-8.0.1.0.0.dist-info/namespace_packages.txt
